agdat/__init__.py
agdat-0.0.2.dist-info/METADATA
agdat-0.0.2.dist-info/WHEEL
agdat-0.0.2.dist-info/top_level.txt
agdat-0.0.2.dist-info/RECORD
